pydx12/__init__.py
pydx12/api.cp310-win_amd64.pyd
pydx12/api.pyi
pydx12-0.1.dist-info/LICENSE
pydx12-0.1.dist-info/METADATA
pydx12-0.1.dist-info/WHEEL
pydx12-0.1.dist-info/top_level.txt
pydx12-0.1.dist-info/RECORD
